tomlenv/__init__.py
tomlenv/_parser.py
tomlenv-0.2.3.dist-info/LICENSE
tomlenv-0.2.3.dist-info/METADATA
tomlenv-0.2.3.dist-info/WHEEL
tomlenv-0.2.3.dist-info/RECORD
