Metadata-Version: 2.3
Name: tomlenv
Version: 0.2.3
Summary: Environment Wrapped TOML
License: MIT
Keywords: TOML,environment,variables,config
Author: João Santos
Author-email: joaopns05@gmail.com
Requires-Python: >=3.11,<4.0
Classifier: Development Status :: 4 - Beta
Classifier: Intended Audience :: Developers
Classifier: License :: OSI Approved :: MIT License
Classifier: Programming Language :: Python :: 3
Classifier: Programming Language :: Python :: 3.11
Classifier: Programming Language :: Python :: 3.12
Classifier: Programming Language :: Python :: 3.13
Classifier: Topic :: Software Development :: Libraries :: Python Modules
Project-URL: Repository, https://github.com/joaonsantos/tomlenv
